guiltytargets/__init__.py
guiltytargets/__main__.py
guiltytargets/cli.py
guiltytargets/constants.py
guiltytargets/download.py
guiltytargets/gat2vec.py
guiltytargets/pipeline.py
guiltytargets/ppi_network_annotation/__init__.py
guiltytargets/ppi_network_annotation/parsers.py
guiltytargets/ppi_network_annotation/pipeline.py
guiltytargets/ppi_network_annotation/model/__init__.py
guiltytargets/ppi_network_annotation/model/attribute_network.py
guiltytargets/ppi_network_annotation/model/filtered_network.py
guiltytargets/ppi_network_annotation/model/gene.py
guiltytargets/ppi_network_annotation/model/labeled_network.py
guiltytargets/ppi_network_annotation/model/neighborhood_network.py
guiltytargets/ppi_network_annotation/model/network.py
guiltytargets-0.0.2.dist-info/LICENSE
guiltytargets-0.0.2.dist-info/METADATA
guiltytargets-0.0.2.dist-info/WHEEL
guiltytargets-0.0.2.dist-info/entry_points.txt
guiltytargets-0.0.2.dist-info/top_level.txt
guiltytargets-0.0.2.dist-info/RECORD
