Metadata-Version: 2.1
Name: guiltytargets
Version: 0.0.2
Summary: A tool for ranking potential targets for a given disease
Home-page: https://github.com/guiltytargets/guiltytargets
Author: Özlem Muslu
Author-email: ozlemmuslu@gmail.com
Maintainer: Charles Tapley Hoyt
Maintainer-email: cthoyt@gmail.com
License: MIT
Download-URL: https://github.com/guiltytargets/guiltytargets/releases
Project-URL: Bug Tracker, https://github.com/guiltytargets/guiltytargets/issues
Project-URL: Source Code, https://github.com/guiltytargets/guiltytargets
Project-URL: Documentation, https://guiltytargets.readthedocs.io
Keywords: Target Prioritization,Network Representation Learning,Knowledge Graph Embeddings,Systems Biology,Networks Biology
Platform: UNKNOWN
Classifier: Development Status :: 4 - Beta
Classifier: Environment :: Console
Classifier: Intended Audience :: Developers
Classifier: Intended Audience :: Science/Research
Classifier: License :: OSI Approved :: MIT License
Classifier: Operating System :: OS Independent
Classifier: Programming Language :: Python
Classifier: Programming Language :: Python :: 3.8
Classifier: Programming Language :: Python :: 3.7
Classifier: Programming Language :: Python :: 3.6
Classifier: Programming Language :: Python :: 3 :: Only
Classifier: Topic :: Scientific/Engineering :: Bio-Informatics
Requires-Python: >=3.6
Requires-Dist: numpy
Requires-Dist: pandas
Requires-Dist: scipy
Requires-Dist: scikit-learn
Requires-Dist: python-igraph
Requires-Dist: click
Requires-Dist: tqdm
Requires-Dist: easy-config
Requires-Dist: mygene
Requires-Dist: opentargets
Requires-Dist: dataclasses-json
Provides-Extra: docs
Requires-Dist: sphinx ; extra == 'docs'
Requires-Dist: sphinx-rtd-theme ; extra == 'docs'
Requires-Dist: sphinx-click ; extra == 'docs'
Requires-Dist: sphinx-autodoc-typehints ; extra == 'docs'
